{"vec_file_metadata":[{"filename":"cargo.toml","filedate":"1589454526.284785100s"},{"filename":"src/all_summary_mod.rs","filedate":"1589449186.593107700s"},{"filename":"src/crev_query_mod.rs","filedate":"1589454111.261310000s"},{"filename":"src/crev_query_templating_mod.rs","filedate":"1589449186.593107700s"},{"filename":"src/duration_mod.rs","filedate":"1589369237.110785200s"},{"filename":"src/html_template_mod.rs","filedate":"1589449308.582306800s"},{"filename":"src/info_mod.rs","filedate":"1589454524.015608300s"},{"filename":"src/issue_mod.rs","filedate":"1589449186.593107700s"},{"filename":"src/main.rs","filedate":"1589450841.269533200s"},{"filename":"src/proof_mod.rs","filedate":"1589449186.593107700s"},{"filename":"src/utils_mod.rs","filedate":"1589454397.823938300s"},{"filename":"src/version_summary_mod.rs","filedate":"1589449186.593107700s"}]}