{"vec_file_metadata":[{"filename":"cargo.toml","filedate":"1590781289.947730200s"},{"filename":"src/author_reviews_mod.rs","filedate":"1590780745.886962500s"},{"filename":"src/crate_reviews_mod.rs","filedate":"1590780737.321167400s"},{"filename":"src/crate_version_summary_mod.rs","filedate":"1590582116.011565400s"},{"filename":"src/data_file_scan_mod.rs","filedate":"1590582116.034242900s"},{"filename":"src/html_server_template_mod.rs","filedate":"1590781285.089966500s"},{"filename":"src/info_group_by_author_mod.rs","filedate":"1590582116.090980500s"},{"filename":"src/info_group_by_crate_mod.rs","filedate":"1590582116.111661600s"},{"filename":"src/issue_mod.rs","filedate":"1590582116.131619200s"},{"filename":"src/main.rs","filedate":"1590662912.455106100s"},{"filename":"src/reserved_folder_mod.rs","filedate":"1590599532.461881900s"},{"filename":"src/review_index_mod.rs","filedate":"1590582116.216782000s"},{"filename":"src/review_index_summary_mod.rs","filedate":"1590582116.230778200s"},{"filename":"src/review_mod.rs","filedate":"1590648156.971662800s"},{"filename":"src/review_new_mod.rs","filedate":"1590663061.688554400s"},{"filename":"src/url_encode_mod.rs","filedate":"1590398141.034239300s"},{"filename":"src/utils_mod.rs","filedate":"1590582116.271408300s"},{"filename":"src/version_summary_mod.rs","filedate":"1590582116.286755500s"}]}